realsense_robotraconteur_driver/__init__.py
realsense_robotraconteur_driver/__main__.py
realsense_robotraconteur_driver/realsense_robotraconteur_driver.py
realsense_robotraconteur_driver-0.2.0.dist-info/METADATA
realsense_robotraconteur_driver-0.2.0.dist-info/WHEEL
realsense_robotraconteur_driver-0.2.0.dist-info/entry_points.txt
realsense_robotraconteur_driver-0.2.0.dist-info/top_level.txt
realsense_robotraconteur_driver-0.2.0.dist-info/RECORD
