Metadata-Version: 2.1
Name: realsense-robotraconteur-driver
Version: 0.2.0
Summary: Robot Raconteur driver for Intel RealSense cameras
Author-email: Honglu He <hehonglu123@gmail.com>, John Wason <wason@wasontech.com>
License: Apache-2.0
Project-URL: homepage, https://github.com/robotraconteur-contrib/realsense_robotraconteur_driver
Project-URL: repository, https://github.com/robotraconteur-contrib/realsense_robotraconteur_driver
Requires-Python: >=3.6
Requires-Dist: robotraconteur
Requires-Dist: robotraconteurcompanion
Requires-Dist: drekar-launch-process
Requires-Dist: opencv-contrib-python
Requires-Dist: matplotlib
Requires-Dist: pyrealsense2
Provides-Extra: test
Requires-Dist: pytest; extra == "test"
